{
  "_format": "hh-sol-cache-2",
  "files": {
    "/Users/user/Desktop/gramps/contracts/GrampsCare.sol": {
      "lastModificationDate": 1767342485199,
      "contentHash": "16b44df3f7643943060a9fa1f95a0d55",
      "sourceName": "contracts/GrampsCare.sol",
      "solcConfig": {
        "version": "0.8.19",
        "settings": {
          "optimizer": {
            "enabled": false,
            "runs": 200
          },
          "outputSelection": {
            "*": {
              "*": [
                "abi",
                "evm.bytecode",
                "evm.deployedBytecode",
                "evm.methodIdentifiers",
                "metadata"
              ],
              "": [
                "ast"
              ]
            }
          }
        }
      },
      "imports": [],
      "versionPragmas": [
        "^0.8.19"
      ],
      "artifacts": [
        "GrampsCare"
      ]
    }
  }
}
